Metadata-Version: 2.1
Name: Simfloat
Version: 0.2
Summary: Simulate binary floating point representations and arithmetic to IEEE 754 standards of arbitrary fixed precision, or to infinite precision, and different rounding modes
Home-page: https://github.com/robclewley/ieee754_simulation
Author: Rob Clewley
License: BSD 2-Clause
Platform: UNKNOWN
Classifier: License :: OSI Approved :: BSD License
Classifier: Programming Language :: Python :: 3
Classifier: Operating System :: OS Independent
Classifier: Development Status :: 5 - Production/Stable
Classifier: Topic :: Education
Classifier: Topic :: Scientific/Engineering
